MANIFEST.in
README.rst
setup.cfg
setup.py
docs/HISTORY.rst
docs/INSTALL.rst
docs/LICENSE.GPL
docs/LICENSE.rst
redomino/__init__.py
redomino.appytransforms.egg-info/PKG-INFO
redomino.appytransforms.egg-info/SOURCES.txt
redomino.appytransforms.egg-info/dependency_links.txt
redomino.appytransforms.egg-info/entry_points.txt
redomino.appytransforms.egg-info/namespace_packages.txt
redomino.appytransforms.egg-info/not-zip-safe
redomino.appytransforms.egg-info/requires.txt
redomino.appytransforms.egg-info/top_level.txt
redomino/appytransforms/__init__.py
redomino/appytransforms/config.py
redomino/appytransforms/configure.zcml
redomino/appytransforms/mimetype.py
redomino/appytransforms/setuphandlers.py
redomino/appytransforms/testing.py
redomino/appytransforms/Extensions/Install.py
redomino/appytransforms/profiles/default/metadata.xml
redomino/appytransforms/profiles/default/redomino.appytransforms.txt
redomino/appytransforms/profiles/uninstall/redomino.appytransforms_uninstall.txt
redomino/appytransforms/tests/__init__.py
redomino/appytransforms/tests/input.ods
redomino/appytransforms/tests/input.odt
redomino/appytransforms/tests/input1.ods
redomino/appytransforms/tests/input1.odt
redomino/appytransforms/tests/input2.odt
redomino/appytransforms/tests/input3.odt
redomino/appytransforms/tests/test_ods_transform.py
redomino/appytransforms/tests/test_odt_transform.py
redomino/appytransforms/tests/test_portal.py
redomino/appytransforms/tests/test_uninstall.py
redomino/appytransforms/transforms/__init__.py
redomino/appytransforms/transforms/ods_transform.py
redomino/appytransforms/transforms/odt_transform.py