Metadata-Version: 1.0
Name: redomino.appytransforms
Version: 0.1
Summary: ODT/ODS templating transforms for Plone
Home-page: https://github.com/redomino/redomino.appytransforms
Author: Davide Moro
Author-email: davide.moro@redomino.com
License: GPL
Keywords: plone
Platform: UNKNOWN
Classifier: Framework :: Plone
Classifier: Programming Language :: Python
Classifier: Intended Audience :: Developers
Classifier: License :: OSI Approved :: GNU General Public License (GPL)
Classifier: Programming Language :: Python :: 2.6
Classifier: Programming Language :: Python :: 2.7
Classifier: Topic :: Text Processing
